aiohttp_zlib_ng/__init__.py
aiohttp_zlib_ng/py.typed
aiohttp_zlib_ng-0.3.2.dist-info/LICENSE
aiohttp_zlib_ng-0.3.2.dist-info/METADATA
aiohttp_zlib_ng-0.3.2.dist-info/WHEEL
aiohttp_zlib_ng-0.3.2.dist-info/RECORD
