Metadata-Version: 2.1
Name: aiohttp-zlib-ng
Version: 0.3.2
Summary: Enable zlib_ng on aiohttp
Home-page: https://github.com/bdraco/aiohttp-zlib-ng
Author: J. Nick Koston
Author-email: nick@koston.org
Requires-Python: >=3.8,<4.0
Classifier: Development Status :: 2 - Pre-Alpha
Classifier: Intended Audience :: Developers
Classifier: License :: OSI Approved :: Apache Software License
Classifier: Natural Language :: English
Classifier: Operating System :: OS Independent
Classifier: Programming Language :: Python :: 3
Classifier: Programming Language :: Python :: 3.8
Classifier: Programming Language :: Python :: 3.9
Classifier: Programming Language :: Python :: 3.10
Classifier: Programming Language :: Python :: 3.11
Classifier: Programming Language :: Python :: 3.12
Classifier: Topic :: Software Development :: Libraries
Provides-Extra: isal
Requires-Dist: aiohttp (>=3.8.5)
Requires-Dist: isal (>=1.5.3) ; (platform_machine == "x86_64" or platform_machine == "AMD64" or platform_machine == "aarch64" or platform_machine == "arm64") and (extra == "isal")
Requires-Dist: zlib-ng (>=0.3.0)
Project-URL: Bug Tracker, https://github.com/bdraco/aiohttp-zlib-ng/issues
Project-URL: Changelog, https://github.com/bdraco/aiohttp-zlib-ng/blob/main/CHANGELOG.md
Project-URL: Repository, https://github.com/bdraco/aiohttp-zlib-ng
